binhoshell/__init__.py
binhoshell/shell.py
shellpy/__init__.py
shellpy/shell.py
binhoshell-0.2.3.dist-info/METADATA
binhoshell-0.2.3.dist-info/WHEEL
binhoshell-0.2.3.dist-info/top_level.txt
binhoshell-0.2.3.dist-info/RECORD
