Metadata-Version: 2.1
Name: binhoshell
Version: 0.2.3
Summary: A shell in python (???)
Home-page: https://bitbucket.org/paikka/shellpy/src
Author: Fábio
Author-email: fabio@paikka.me
License: MIT
Platform: UNKNOWN
